<?xml version="1.0"?>
<!DOCTYPE hibernate-mapping PUBLIC "-//Hibernate/Hibernate Mapping DTD 3.0//EN"
"http://hibernate.sourceforge.net/hibernate-mapping-3.0.dtd">
<!-- Generated 13/12/2012 11:35:29 AM by Hibernate Tools 3.4.0.CR1 -->
<hibernate-mapping>
    <class name="com.hildebrando.visado.modelo.TiivsFeriado" table="TIIVS_FERIADO">
        <id name="idFeriado" type="int">
            <column name="ID_FERIADO" precision="8" scale="0" />
            <generator class="sequence">
            	<param name="sequence">SEQ_FERIADO</param>
            </generator>
        </id>
        <property name="fecha" type="date">
            <column name="FECHA" length="7" />
        </property>
        <property name="indicador" type="java.lang.Character">
            <column name="INDICADOR" length="1" />
        </property>
        <property name="codDist" type="string">
            <column name="COD_DIST" length="7" />
        </property>
        <property name="estado" type="java.lang.Character">
            <column name="ESTADO" length="1" />
        </property>
    </class>
</hibernate-mapping>
